{
    "Ar36": {
        "error": 1.8200283247525548,
        "error_type": "SEM",
        "filter_outliers_dict": {
            "filter_outliers": true,
            "iterations": 1,
            "std_devs": 2
        },
        "fit": "linear",
        "value": 313.3612132363986
    },
    "Ar37": {
        "error": 2.1570542446030795e-06,
        "error_type": "SEM",
        "filter_outliers_dict": {
            "filter_outliers": true,
            "iterations": 1,
            "std_devs": 2
        },
        "fit": "linear",
        "value": -2.9459385799182864e-05
    },
    "Ar38": {
        "error": 2.1886252373722334e-06,
        "error_type": "SEM",
        "filter_outliers_dict": {
            "filter_outliers": true,
            "iterations": 1,
            "std_devs": 2
        },
        "fit": "linear",
        "value": 3.0001746007682535e-05
    },
    "Ar39": {
        "error": 2.9281975276596697e-07,
        "error_type": "SEM",
        "filter_outliers_dict": {
            "filter_outliers": true,
            "iterations": 1,
            "std_devs": 2
        },
        "fit": "linear",
        "value": -2.6508493822870187e-05
    },
    "Ar40": {
        "error": 3.499375401783107e-06,
        "error_type": "SEM",
        "filter_outliers_dict": {
            "filter_outliers": true,
            "iterations": 1,
            "std_devs": 2
        },
        "fit": "linear",
        "value": 0.0003918756897598045
    }
}